{"webApplication":{"name":"SampleApplication","version":"1.0.0","environment":"Sample Application","gitRepoUrl":"","gitBranchName":"master","initiatedBy":"dev"},"auditResultList":[{"auditInstanceId":"812e0077-763f-4d5d-b64a-4c6681ed7965","initiatedBy":"dev","executionEnvironment":"Sample Application","startDateTime":"2023-05-30T12:11:04.878Z","endDateTime":"2023-05-30T12:13:18.351Z","networkThrottle":12500,"cpuSlowDownMultiplier":0,"loadTimeInteractive":809.761,"loadTimeSpeedIndex":1122},{"auditInstanceId":"812e0077-763f-4d5d-b64a-4c6681ed7965","initiatedBy":"dev","executionEnvironment":"Sample Application","startDateTime":"2023-05-30T12:11:50.273Z","endDateTime":"2023-05-30T12:13:18.360Z","networkThrottle":20500,"cpuSlowDownMultiplier":0,"loadTimeInteractive":711.319,"loadTimeSpeedIndex":1168},{"auditInstanceId":"812e0077-763f-4d5d-b64a-4c6681ed7965","initiatedBy":"dev","executionEnvironment":"Sample Application","startDateTime":"2023-05-30T12:12:35.208Z","endDateTime":"2023-05-30T12:13:18.367Z","networkThrottle":29500,"cpuSlowDownMultiplier":0,"loadTimeInteractive":624.959,"loadTimeSpeedIndex":984},{"auditInstanceId":"812e0077-763f-4d5d-b64a-4c6681ed7965","initiatedBy":"dev","executionEnvironment":"Sample Application","startDateTime":"2023-05-30T12:10:16.805Z","endDateTime":"2023-05-30T12:13:18.378Z","networkThrottle":9500,"cpuSlowDownMultiplier":0,"loadTimeInteractive":2827.369,"loadTimeSpeedIndex":2523},{"auditInstanceId":"812e0077-763f-4d5d-b64a-4c6681ed7965","initiatedBy":"dev","executionEnvironment":"Sample Application","startDateTime":"2023-05-30T12:11:27.405Z","endDateTime":"2023-05-30T12:13:18.386Z","networkThrottle":12500,"cpuSlowDownMultiplier":2,"loadTimeInteractive":1859.845,"loadTimeSpeedIndex":1391},{"auditInstanceId":"812e0077-763f-4d5d-b64a-4c6681ed7965","initiatedBy":"dev","executionEnvironment":"Sample Application","startDateTime":"2023-05-30T12:12:12.469Z","endDateTime":"2023-05-30T12:13:18.394Z","networkThrottle":20500,"cpuSlowDownMultiplier":2,"loadTimeInteractive":2282.708,"loadTimeSpeedIndex":1330},{"auditInstanceId":"812e0077-763f-4d5d-b64a-4c6681ed7965","initiatedBy":"dev","executionEnvironment":"Sample Application","startDateTime":"2023-05-30T12:12:57.287Z","endDateTime":"2023-05-30T12:13:18.407Z","networkThrottle":29500,"cpuSlowDownMultiplier":2,"loadTimeInteractive":1237.499,"loadTimeSpeedIndex":1337},{"auditInstanceId":"812e0077-763f-4d5d-b64a-4c6681ed7965","initiatedBy":"dev","executionEnvironment":"Sample Application","startDateTime":"2023-05-30T12:10:41.879Z","endDateTime":"2023-05-30T12:13:18.414Z","networkThrottle":9500,"cpuSlowDownMultiplier":2,"loadTimeInteractive":1492.113,"loadTimeSpeedIndex":1552}]}