{"webPage":{"url":"https://support.google.com/","id":"Google_Support_Page","environment":"LP","displayName":"Google Support Home Page ","description":"Sample Description"},"webApplication":{"id":"google.com","name":"google.com","version":"1.0.0","gitRepoUrl":"","gitBranchName":"master"},"cpuSlowDownMultiplier":2,"networkSpeed":19500,"labels":["2023-06-01T06:23:15.786Z-64a55967-683d-4c46-acf7-2bb4fc3340d4","2023-06-01T07:08:45.868Z-65838c93-55c9-48a9-9261-56b847e93c49","2023-06-01T06:46:02.008Z-7fe1f9f5-4915-4723-b98a-f30ef29cb308"],"listOfDataSets":{"interactive":[2005.81,1785.298,1831.741],"speedindex":[1207,1152,1110]}}