{"webPage":{"url":"https://support.google.com/","id":"Google_Support_Page","environment":"LP","displayName":"Google Support Home Page ","description":"Sample Description"},"webApplication":{"id":"google.com","name":"google.com","version":"1.0.0","gitRepoUrl":"","gitBranchName":"master"},"auditInstanceId":"7fe1f9f5-4915-4723-b98a-f30ef29cb308","startDateTime":"2023-06-01T06:41:54.780Z","endDateTime":"2023-06-01T06:42:23.712Z","networkThrottle":{"rttMs":100,"throughputKbps":12500},"cpuSlowDownMultiplier":0,"loadTimeInteractive":1338.647,"loadTimeSpeedIndex":1077}